[{"name":"reactive_database","qualifiedName":"reactive_database","href":"reactive_database/reactive_database-library.html","type":"library","overriddenDepth":0},{"name":"ReactiveDatabase","qualifiedName":"reactive_database.ReactiveDatabase","href":"reactive_database/ReactiveDatabase-class.html","type":"class","overriddenDepth":0,"enclosedBy":{"name":"reactive_database","type":"library"}},{"name":"operator ==","qualifiedName":"reactive_database.ReactiveDatabase.==","href":"reactive_database/ReactiveDatabase/operator_equals.html","type":"method","overriddenDepth":0,"enclosedBy":{"name":"ReactiveDatabase","type":"class"}},{"name":"close","qualifiedName":"reactive_database.ReactiveDatabase.close","href":"reactive_database/ReactiveDatabase/close.html","type":"method","overriddenDepth":0,"enclosedBy":{"name":"ReactiveDatabase","type":"class"}},{"name":"delete","qualifiedName":"reactive_database.ReactiveDatabase.delete","href":"reactive_database/ReactiveDatabase/delete.html","type":"method","overriddenDepth":0,"enclosedBy":{"name":"ReactiveDatabase","type":"class"}},{"name":"ReactiveDatabase.from","qualifiedName":"reactive_database.ReactiveDatabase.from","href":"reactive_database/ReactiveDatabase/ReactiveDatabase.from.html","type":"constructor","overriddenDepth":0,"enclosedBy":{"name":"ReactiveDatabase","type":"class"}},{"name":"hashCode","qualifiedName":"reactive_database.ReactiveDatabase.hashCode","href":"reactive_database/ReactiveDatabase/hashCode.html","type":"property","overriddenDepth":0,"enclosedBy":{"name":"ReactiveDatabase","type":"class"}},{"name":"insert","qualifiedName":"reactive_database.ReactiveDatabase.insert","href":"reactive_database/ReactiveDatabase/insert.html","type":"method","overriddenDepth":0,"enclosedBy":{"name":"ReactiveDatabase","type":"class"}},{"name":"logging","qualifiedName":"reactive_database.ReactiveDatabase.logging","href":"reactive_database/ReactiveDatabase/logging.html","type":"property","overriddenDepth":0,"enclosedBy":{"name":"ReactiveDatabase","type":"class"}},{"name":"noSuchMethod","qualifiedName":"reactive_database.ReactiveDatabase.noSuchMethod","href":"reactive_database/ReactiveDatabase/noSuchMethod.html","type":"method","overriddenDepth":0,"enclosedBy":{"name":"ReactiveDatabase","type":"class"}},{"name":"notifyTrigger","qualifiedName":"reactive_database.ReactiveDatabase.notifyTrigger","href":"reactive_database/ReactiveDatabase/notifyTrigger.html","type":"method","overriddenDepth":0,"enclosedBy":{"name":"ReactiveDatabase","type":"class"}},{"name":"query","qualifiedName":"reactive_database.ReactiveDatabase.query","href":"reactive_database/ReactiveDatabase/query.html","type":"method","overriddenDepth":0,"enclosedBy":{"name":"ReactiveDatabase","type":"class"}},{"name":"runtimeType","qualifiedName":"reactive_database.ReactiveDatabase.runtimeType","href":"reactive_database/ReactiveDatabase/runtimeType.html","type":"property","overriddenDepth":0,"enclosedBy":{"name":"ReactiveDatabase","type":"class"}},{"name":"toString","qualifiedName":"reactive_database.ReactiveDatabase.toString","href":"reactive_database/ReactiveDatabase/toString.html","type":"method","overriddenDepth":0,"enclosedBy":{"name":"ReactiveDatabase","type":"class"}},{"name":"update","qualifiedName":"reactive_database.ReactiveDatabase.update","href":"reactive_database/ReactiveDatabase/update.html","type":"method","overriddenDepth":0,"enclosedBy":{"name":"ReactiveDatabase","type":"class"}},{"name":"reactive_sqflite","qualifiedName":"reactive_sqflite","href":"reactive_sqflite/reactive_sqflite-library.html","type":"library","overriddenDepth":0}]
